Metadata-Version: 2.1
Name: AleksFolt
Version: 0.1
Summary: Полезная библиотека
Author: AleksFolt
Author-email: dfdfdd039@gmail.com
